{
    "Gastronomía Colombiana": [
    
        {
            "Nombre": "Alitas con Salsa Artesanal de Panela",
            "Img": "../img/Alitas con Salsa Artesanal de Panela.png",
            "Acompañante": "Ensalada",
            "AcompañanteDos": "Tajadas de Plátano Maduro",
            "AcompañanteTres": "Frijoles",
            "Estrellas": "⭐⭐⭐⭐⭐",
            "Precio": "$ 30.000"
        },
        {
            "Nombre": "Arroz Coco con Camarón",
            "Img": "../img/Arroz Coco con Camarón.png",
            "Acompañante": "Puré de Yuca",
            "AcompañanteDos": "Vegetales Salteados",
            "AcompañanteTres": "Patacones",
            "Estrellas": "⭐⭐⭐⭐",
            "Precio": "$ 35.000"
        },
        {
            "Nombre": "Arroz Atollado",
            "Img": "../img/Arroz Atollado.png",
            "Acompañante": "Aguacate",
            "AcompañanteDos": "Yuca Frita",
            "AcompañanteTres": "Salsa de Tomate",
            "Estrellas": "⭐⭐⭐",
            "Precio": "$ 25.000"
        },
        {
            "Nombre": "Arroz Atollado con Carne Ahumada",
            "Img": "../img/Arroz Atollado con Carne Ahumada.png",
            "Acompañante": "Ensalada de Repollo",
            "AcompañanteDos": "Puré de Plátano",
            "AcompañanteTres": "Salsa Barbacoa",
            "Estrellas": "⭐⭐⭐⭐",
            "Precio": "$ 40.000"
        }
    ]
}
