{
    "Gastronomía Japonesa": [
        {
            "Nombre": "Sushi",
            "Img": "",
            "Acompañante": "Salsa de soja",
            "AcompañanteDos": "Wasabi",
            "AcompañanteTres": "Jengibre encurtido",
            "Estrellas": "⭐⭐⭐⭐",
            "Precio": "$ 35.000"
        },
        {
            "Nombre": "Onigiri",
            "Img": "",
            "Acompañante": "Sésamo tostado",
            "AcompañanteDos": "Alga nori",
            "AcompañanteTres": "Relleno de tu elección",
            "Estrellas": "⭐⭐⭐",
            "Precio": "$ 25.000"
        },
        {
            "Nombre": "Sashimi",
            "Img": "",
            "Acompañante": "Salsa de soja",
            "AcompañanteDos": "Wasabi",
            "AcompañanteTres": "Rodajas de rábano",
            "Estrellas": "⭐⭐⭐⭐",
            "Precio": "$ 40.000"
        },
        {
            "Nombre": "Sopa de miso",
            "Img": "",
            "Acompañante": "Tofu",
            "AcompañanteDos": "Algas wakame",
            "AcompañanteTres": "Cebollín",
            "Estrellas": "⭐⭐⭐",
            "Precio": "$ 20.000"
        }
    ]
}